samsung_ru7179_remote/__init__.py
samsung_ru7179_remote/auth.py
samsung_ru7179_remote/commands.py
samsung_ru7179_remote/config.py
samsung_ru7179_remote/key.py
samsung_ru7179_remote-0.1.1.data/scripts/samsung-remote
samsung_ru7179_remote-0.1.1.dist-info/LICENSE
samsung_ru7179_remote-0.1.1.dist-info/METADATA
samsung_ru7179_remote-0.1.1.dist-info/WHEEL
samsung_ru7179_remote-0.1.1.dist-info/top_level.txt
samsung_ru7179_remote-0.1.1.dist-info/RECORD
