Metadata-Version: 2.1
Name: samsung-ru7179-remote
Version: 0.1.1
Summary: A remote for Samsung RU7179 TVs
Home-page: https://gitlab.namibsun.net/namibsun/python/samsung-ru7179-remote
Author: Hermann Krumrey
Author-email: hermann@krumreyh.com
License: GNU GPL3
Platform: UNKNOWN
Classifier: License :: OSI Approved :: GNU General Public License v3 (GPLv3)
Requires-Dist: typing
Requires-Dist: puffotter
Requires-Dist: websocket-client
